py_aurum/__init__.py
py_aurum/py_aurum.py
py_aurum-0.1.17.dist-info/LICENSE
py_aurum-0.1.17.dist-info/METADATA
py_aurum-0.1.17.dist-info/WHEEL
py_aurum-0.1.17.dist-info/top_level.txt
py_aurum-0.1.17.dist-info/RECORD
